jupyter_repl/__init__.py
jupyter_repl/_version.py
jupyter_repl/handlers.py
jupyter_repl/tests/__init__.py
jupyter_repl/tests/test_handlers.py
jupyter_repl-0.0.3.data/data/etc/jupyter/jupyter_notebook_config.d/jupyter_repl.json
jupyter_repl-0.0.3.data/data/etc/jupyter/jupyter_server_config.d/jupyter_repl.json
jupyter_repl-0.0.3.data/data/share/jupyter/labextensions/@datalayer/jupyter-repl/build_log.json
jupyter_repl-0.0.3.data/data/share/jupyter/labextensions/@datalayer/jupyter-repl/package.json
jupyter_repl-0.0.3.data/data/share/jupyter/labextensions/@datalayer/jupyter-repl/schemas/@datalayer/jupyter-repl/package.json.orig
jupyter_repl-0.0.3.data/data/share/jupyter/labextensions/@datalayer/jupyter-repl/schemas/@datalayer/jupyter-repl/plugin.json
jupyter_repl-0.0.3.data/data/share/jupyter/labextensions/@datalayer/jupyter-repl/static/lib_index_js.56f2b12d87ebd350a071.js
jupyter_repl-0.0.3.data/data/share/jupyter/labextensions/@datalayer/jupyter-repl/static/lib_index_js.56f2b12d87ebd350a071.js.map
jupyter_repl-0.0.3.data/data/share/jupyter/labextensions/@datalayer/jupyter-repl/static/node_modules_object-assign_index_js.b68b576877995a8b6478.js
jupyter_repl-0.0.3.data/data/share/jupyter/labextensions/@datalayer/jupyter-repl/static/node_modules_object-assign_index_js.b68b576877995a8b6478.js.map
jupyter_repl-0.0.3.data/data/share/jupyter/labextensions/@datalayer/jupyter-repl/static/remoteEntry.a67e48c5aabada28ad1d.js
jupyter_repl-0.0.3.data/data/share/jupyter/labextensions/@datalayer/jupyter-repl/static/remoteEntry.a67e48c5aabada28ad1d.js.map
jupyter_repl-0.0.3.data/data/share/jupyter/labextensions/@datalayer/jupyter-repl/static/style.js
jupyter_repl-0.0.3.data/data/share/jupyter/labextensions/@datalayer/jupyter-repl/static/style_index_js.d575b2660040263e727c.js
jupyter_repl-0.0.3.data/data/share/jupyter/labextensions/@datalayer/jupyter-repl/static/style_index_js.d575b2660040263e727c.js.map
jupyter_repl-0.0.3.dist-info/METADATA
jupyter_repl-0.0.3.dist-info/WHEEL
jupyter_repl-0.0.3.dist-info/licenses/LICENSE
jupyter_repl-0.0.3.dist-info/RECORD
